Metadata-Version: 1.1
Name: cbs
Version: 1.0.0
Summary: List coverage blind spots
Home-page: https://github.com/christofsteel/cbs
Author: Christoph Stahl
Author-email: christoph.stahl@uni-dortmund.de
License: MIT
Download-URL: https://github.com/christofsteel/cbs/tarball/1.0
Platform: UNKNOWN
Classifier: Development Status :: 5 - Production/Stable
Classifier: Environment :: Console
Classifier: Intended Audience :: Science/Research
Classifier: Topic :: Scientific/Engineering :: Bio-Informatics
Classifier: Topic :: Scientific/Engineering :: Medical Science Apps.
Classifier: License :: OSI Approved :: MIT License
Classifier: Programming Language :: Python :: 3
Classifier: Programming Language :: Python :: 3.3
Classifier: Programming Language :: Python :: 3.4
Classifier: Programming Language :: Python :: 3.5
